[
  {
    "id": "1188",
    "away": "BOS",
    "home": "WSH",
    "date": "2024-12-31T17:30:00",
    "awayVotes": 104,
    "homeVotes": 109,
    "awayPercent": 49,
    "homePercent": 51,
    "homeOdds": 1.9607843137254901,
    "awayOdds": 2.0408163265306123
  },
  {
    "id": "1189",
    "away": "NYI",
    "home": "TOR",
    "date": "2024-12-31T18:00:00",
    "awayVotes": 13,
    "homeVotes": 18,
    "awayPercent": 42,
    "homePercent": 58,
    "homeOdds": 1.7241379310344827,
    "awayOdds": 2.380952380952381
  },
  {
    "id": "1190",
    "away": "MTL",
    "home": "VGK",
    "date": "2024-12-31T20:00:00",
    "awayVotes": 18,
    "homeVotes": 6,
    "awayPercent": 75,
    "homePercent": 25,
    "homeOdds": 4,
    "awayOdds": 1.3333333333333333
  },
  {
    "id": "1191",
    "away": "STL",
    "home": "CHI",
    "date": "2024-12-31T22:00:00",
    "awayVotes": 3,
    "homeVotes": 10,
    "awayPercent": 23,
    "homePercent": 77,
    "homeOdds": 1.2987012987012987,
    "awayOdds": 4.3478260869565215
  },
  {
    "id": "1192",
    "away": "PIT",
    "home": "DET",
    "date": "2025-01-01T01:00:00",
    "awayVotes": 2,
    "homeVotes": 3,
    "awayPercent": 40,
    "homePercent": 60,
    "homeOdds": 1.6666666666666667,
    "awayOdds": 2.5
  }
]